[
  {
      "gramsGelatin": 10,
      "water": 60.0,
      "celsius": 40.0
  },
  [
    {
      "tag": "ADDITION",
      "solutions": [
        [
          {
            "salts": [
              {
                "tag": "NaBr",
                "gramAmount": 3.9
              }
            ]
          },
          {
            "amountAdded": 1.0,
            "overSeconds": 0.0
          }
        ]
      ]
    },
    {
      "tag": "TEMPERATURE",
      "newCelsius": 55.0
    },
    {
      "tag": "ADDITION",
      "solutions": [
        [
          {
            "otherChemicals": [
              {
                "name": "Rhodium Chloride",
                "amount": 0.09,
                "unit": "MILLILITER",
                "conc": 0.1
              }
            ]
          },
          {
            "amountAdded": 1.0,
            "overSeconds": 0.0
          }
        ]
      ]
    },
    {
      "tag": "ADDITION",
      "solutions": [
        [
          {
            "silverNitrate": {
              "gramAmounts": 5.1
            },
            "water": 40.0,
            "celsius": 55.0
          },
          {
            "amountAdded": 0.25,
            "overSeconds": 60.0
          }
        ]
      ]
    },
    {
      "tag": "STOP"
    }
  ]
]